fletchck/__init__.py
fletchck/__main__.py
fletchck/action.py
fletchck/check.py
fletchck/defaults.py
fletchck/mclient.py
fletchck/util.py
fletchck/webui.py
fletchck/static/bootstrap.min.css
fletchck/static/calendar2-day.svg
fletchck/static/caret-down.svg
fletchck/static/caret-right-square.svg
fletchck/static/caret-up.svg
fletchck/static/check-circle.svg
fletchck/static/clock-history.svg
fletchck/static/copy.svg
fletchck/static/exclamation-circle.svg
fletchck/static/exclamation-triangle.svg
fletchck/static/fletchck.css
fletchck/static/fletchck.js
fletchck/static/fletchck.svg
fletchck/static/pause-circle.svg
fletchck/static/pencil.svg
fletchck/static/person-circle.svg
fletchck/static/play-btn.svg
fletchck/static/power.svg
fletchck/static/x-circle.svg
fletchck/templates/action.html
fletchck/templates/base.html
fletchck/templates/check.html
fletchck/templates/checks.html
fletchck/templates/config.html
fletchck/templates/dash.html
fletchck/templates/home.html
fletchck/templates/log.html
fletchck/templates/login.html
fletchck/templates/reload.html
fletchck/templates/user.html
fletchck-1.1.4.dist-info/licenses/LICENSE
fletchck-1.1.4.dist-info/METADATA
fletchck-1.1.4.dist-info/WHEEL
fletchck-1.1.4.dist-info/entry_points.txt
fletchck-1.1.4.dist-info/top_level.txt
fletchck-1.1.4.dist-info/RECORD
