Metadata-Version: 2.4
Name: fletchck
Version: 1.1.4
Summary: Machine monitor
Author-email: Nathan Fraser <ndf-zz@6-v.org>
License-Expression: MIT
Project-URL: homepage, https://github.com/ndf-zz/fletchck
Keywords: system,monitor
Classifier: Development Status :: 4 - Beta
Classifier: Topic :: System :: Monitoring
Classifier: Operating System :: OS Independent
Classifier: Programming Language :: Python :: 3
Requires-Python: >=3.11
License-File: LICENSE
Requires-Dist: tornado>=6.3
Requires-Dist: passlib>=1.7
Requires-Dist: APScheduler>=3.11
Requires-Dist: cryptography>=42.0
Requires-Dist: paramiko>=3.5
Requires-Dist: argon2-cffi>=21.2
Requires-Dist: paho-mqtt>=2.1
Requires-Dist: python-dateutil>=2.9
Requires-Dist: dnspython>=2.7
Requires-Dist: psutil>=5.4
Requires-Dist: nut2-notl
Dynamic: license-file
